{"identifier":"demo_lax102","label":"CT 102: Same as case 101 but with annual amortizing paymen","contractType":"LAX","version":"20190902","description":"Same as case 101 but with annual amortizing payments of USD 100.0 for the first 3 years, USD 200.0 for the next 2 years, and 300.0 for the last year.","terms":{"contractType":"LAX","statusDate":"2015-01-01T00:00:00","contractRole":"RPA","contractID":102,"arrayCycleAnchorDateOfInterestPayment":"2016-01-01T00:00:00","arrayCycleOfInterestPayment":"1Y+","nominalInterestRate":0.05,"dayCountConvention":"30E/360","interestCalculationBase":"NT","currency":"USD","contractDealDate":"2015-01-01T00:00:00","initialExchangeDate":"2015-01-02T00:00:00","notionalPrincipal":1000,"arrayCycleAnchorDateOfPrincipalRedemption":"2016-01-01T00,2019-01-01T00,2021-01-01T00:00:00","arrayCycleOfPrincipalRedemption":"1Y+,1Y+,1Y+","arrayNextPrincipalRedemptionPayment":"100,200,300","arrayIncreaseDecrease":"DEC,DEC,DEC","arrayRate":"0"}}
